ayush/__init__.py
ayush/youtube.py
ayush-0.1.3.dist-info/entry_points.txt
ayush-0.1.3.dist-info/WHEEL
ayush-0.1.3.dist-info/METADATA
ayush-0.1.3.dist-info/RECORD
