Metadata-Version: 2.1
Name: ayush
Version: 0.1.3
Summary: personal scripts & stuff; you probably shouldn't use it
Author: Ayush Shanker
Author-email: ayushshanker@outlook.in
Requires-Python: >=3.8,<4.0
Classifier: Programming Language :: Python :: 3
Classifier: Programming Language :: Python :: 3.8
Requires-Dist: hues (>=0.2.2,<0.3.0)
Requires-Dist: pafy (>=0.5.5,<0.6.0)
Requires-Dist: python-slugify (>=4.0.0,<5.0.0)
Requires-Dist: youtube_dl (>=2020.5.3,<2021.0.0)
